[{"time": "2016-01-01", "NY Employment Level": 9305342.0, "NY Employment-Population Ratio": 0.578, "NY Labor Force Level": 9777801.0, "NY Labor Force Participation Rate": 0.607, "NY Unemployment Level": 472459.0, "NY Unemployment Rate": 0.048, "U.S. Employment-Population Ratio": 0.597, "U.S. Labor Force Participation Rate": 0.627, "U.S. Unemployment Rate": 0.048}, {"time": "2016-02-01", "NY Employment Level": 9308167.0, "NY Employment-Population Ratio": 0.578, "NY Labor Force Level": 9779589.0, "NY Labor Force Participation Rate": 0.607, "NY Unemployment Level": 471422.0, "NY Unemployment Rate": 0.048, "U.S. Employment-Population Ratio": 0.598, "U.S. Labor Force Participation Rate": 0.628, "U.S. Unemployment Rate": 0.049}, {"time": "2016-03-01", "NY Employment Level": 9304138.0, "NY Employment-Population Ratio": 0.578, "NY Labor Force Level": 9773761.0, "NY Labor Force Participation Rate": 0.607, "NY Unemployment Level": 469623.0, "NY Unemployment Rate": 0.048, "U.S. Employment-Population Ratio": 0.598, "U.S. Labor Force Participation Rate": 0.63, "U.S. Unemployment Rate": 0.05}, {"time": "2016-04-01", "NY Employment Level": 9296018.0, "NY Employment-Population Ratio": 0.5770000000000001, "NY Labor Force Level": 9764691.0, "NY Labor Force Participation Rate": 0.606, "NY Unemployment Level": 468673.0, "NY Unemployment Rate": 0.048, "U.S. Employment-Population Ratio": 0.597, "U.S. Labor Force Participation Rate": 0.629, "U.S. Unemployment Rate": 0.051}, {"time": "2016-05-01", "NY Employment Level": 9287621.0, "NY Employment-Population Ratio": 0.5760000000000001, "NY Labor Force Level": 9758146.0, "NY Labor Force Participation Rate": 0.605, "NY Unemployment Level": 470525.0, "NY Unemployment Rate": 0.048, "U.S. Employment-Population Ratio": 0.597, "U.S. Labor Force Participation Rate": 0.627, "U.S. Unemployment Rate": 0.048}, {"time": "2016-06-01", "NY Employment Level": 9281266.0, "NY Employment-Population Ratio": 0.5760000000000001, "NY Labor Force Level": 9756519.0, "NY Labor Force Participation Rate": 0.605, "NY Unemployment Level": 475253.0, "NY Unemployment Rate": 0.049, "U.S. Employment-Population Ratio": 0.597, "U.S. Labor Force Participation Rate": 0.627, "U.S. Unemployment Rate": 0.049}, {"time": "2016-07-01", "NY Employment Level": 9278229.0, "NY Employment-Population Ratio": 0.575, "NY Labor Force Level": 9759182.0, "NY Labor Force Participation Rate": 0.605, "NY Unemployment Level": 480953.0, "NY Unemployment Rate": 0.049, "U.S. Employment-Population Ratio": 0.598, "U.S. Labor Force Participation Rate": 0.628, "U.S. Unemployment Rate": 0.048}, {"time": "2016-08-01", "NY Employment Level": 9278605.0, "NY Employment-Population Ratio": 0.575, "NY Labor Force Level": 9764203.0, "NY Labor Force Participation Rate": 0.605, "NY Unemployment Level": 485598.0, "NY Unemployment Rate": 0.05, "U.S. Employment-Population Ratio": 0.598, "U.S. Labor Force Participation Rate": 0.629, "U.S. Unemployment Rate": 0.049}, {"time": "2016-09-01", "NY Employment Level": 9281345.0, "NY Employment-Population Ratio": 0.575, "NY Labor Force Level": 9769629.0, "NY Labor Force Participation Rate": 0.605, "NY Unemployment Level": 488284.0, "NY Unemployment Rate": 0.05, "U.S. Employment-Population Ratio": 0.597, "U.S. Labor Force Participation Rate": 0.629, "U.S. Unemployment Rate": 0.05}, {"time": "2016-10-01", "NY Employment Level": 9286139.0, "NY Employment-Population Ratio": 0.575, "NY Labor Force Level": 9773080.0, "NY Labor Force Participation Rate": 0.605, "NY Unemployment Level": 486941.0, "NY Unemployment Rate": 0.05, "U.S. Employment-Population Ratio": 0.597, "U.S. Labor Force Participation Rate": 0.628, "U.S. Unemployment Rate": 0.049}, {"time": "2016-11-01", "NY Employment Level": 9294636.0, "NY Employment-Population Ratio": 0.575, "NY Labor Force Level": 9774939.0, "NY Labor Force Participation Rate": 0.605, "NY Unemployment Level": 480303.0, "NY Unemployment Rate": 0.049, "U.S. Employment-Population Ratio": 0.597, "U.S. Labor Force Participation Rate": 0.627, "U.S. Unemployment Rate": 0.047}, {"time": "2016-12-01", "NY Employment Level": 9307666.0, "NY Employment-Population Ratio": 0.5760000000000001, "NY Labor Force Level": 9778376.0, "NY Labor Force Participation Rate": 0.605, "NY Unemployment Level": 470710.0, "NY Unemployment Rate": 0.048, "U.S. Employment-Population Ratio": 0.597, "U.S. Labor Force Participation Rate": 0.627, "U.S. Unemployment Rate": 0.047}, {"time": "2017-01-01", "NY Employment Level": 9324353.0, "NY Employment-Population Ratio": 0.5770000000000001, "NY Labor Force Level": 9785983.0, "NY Labor Force Participation Rate": 0.605, "NY Unemployment Level": 461630.0, "NY Unemployment Rate": 0.047, "U.S. Employment-Population Ratio": 0.599, "U.S. Labor Force Participation Rate": 0.628, "U.S. Unemployment Rate": 0.047}, {"time": "2017-02-01", "NY Employment Level": 9344486.0, "NY Employment-Population Ratio": 0.578, "NY Labor Force Level": 9799491.0, "NY Labor Force Participation Rate": 0.606, "NY Unemployment Level": 455005.0, "NY Unemployment Rate": 0.046, "U.S. Employment-Population Ratio": 0.6, "U.S. Labor Force Participation Rate": 0.629, "U.S. Unemployment Rate": 0.046}, {"time": "2017-03-01", "NY Employment Level": 9364375.0, "NY Employment-Population Ratio": 0.579, "NY Labor Force Level": 9816438.0, "NY Labor Force Participation Rate": 0.607, "NY Unemployment Level": 452063.0, "NY Unemployment Rate": 0.046, "U.S. Employment-Population Ratio": 0.602, "U.S. Labor Force Participation Rate": 0.629, "U.S. Unemployment Rate": 0.044000000000000004}, {"time": "2017-04-01", "NY Employment Level": 9381374.0, "NY Employment-Population Ratio": 0.58, "NY Labor Force Level": 9834089.0, "NY Labor Force Participation Rate": 0.608, "NY Unemployment Level": 452715.0, "NY Unemployment Rate": 0.046, "U.S. Employment-Population Ratio": 0.602, "U.S. Labor Force Participation Rate": 0.63, "U.S. Unemployment Rate": 0.044000000000000004}, {"time": "2017-05-01", "NY Employment Level": 9394766.0, "NY Employment-Population Ratio": 0.581, "NY Labor Force Level": 9849999.0, "NY Labor Force Participation Rate": 0.609, "NY Unemployment Level": 455233.0, "NY Unemployment Rate": 0.046, "U.S. Employment-Population Ratio": 0.601, "U.S. Labor Force Participation Rate": 0.628, "U.S. Unemployment Rate": 0.044000000000000004}, {"time": "2017-06-01", "NY Employment Level": 9403710.0, "NY Employment-Population Ratio": 0.581, "NY Labor Force Level": 9861994.0, "NY Labor Force Participation Rate": 0.609, "NY Unemployment Level": 458284.0, "NY Unemployment Rate": 0.046, "U.S. Employment-Population Ratio": 0.601, "U.S. Labor Force Participation Rate": 0.628, "U.S. Unemployment Rate": 0.043}, {"time": "2017-07-01", "NY Employment Level": 9406658.0, "NY Employment-Population Ratio": 0.581, "NY Labor Force Level": 9867628.0, "NY Labor Force Participation Rate": 0.61, "NY Unemployment Level": 460970.0, "NY Unemployment Rate": 0.047, "U.S. Employment-Population Ratio": 0.602, "U.S. Labor Force Participation Rate": 0.629, "U.S. Unemployment Rate": 0.043}, {"time": "2017-08-01", "NY Employment Level": 9403019.0, "NY Employment-Population Ratio": 0.581, "NY Labor Force Level": 9865075.0, "NY Labor Force Participation Rate": 0.609, "NY Unemployment Level": 462056.0, "NY Unemployment Rate": 0.047, "U.S. Employment-Population Ratio": 0.601, "U.S. Labor Force Participation Rate": 0.629, "U.S. Unemployment Rate": 0.044000000000000004}, {"time": "2017-09-01", "NY Employment Level": 9394183.0, "NY Employment-Population Ratio": 0.58, "NY Labor Force Level": 9855369.0, "NY Labor Force Participation Rate": 0.608, "NY Unemployment Level": 461186.0, "NY Unemployment Rate": 0.047, "U.S. Employment-Population Ratio": 0.604, "U.S. Labor Force Participation Rate": 0.631, "U.S. Unemployment Rate": 0.043}, {"time": "2017-10-01", "NY Employment Level": 9382584.0, "NY Employment-Population Ratio": 0.579, "NY Labor Force Level": 9841071.0, "NY Labor Force Participation Rate": 0.607, "NY Unemployment Level": 458487.0, "NY Unemployment Rate": 0.047, "U.S. Employment-Population Ratio": 0.601, "U.S. Labor Force Participation Rate": 0.627, "U.S. Unemployment Rate": 0.042}, {"time": "2017-11-01", "NY Employment Level": 9370253.0, "NY Employment-Population Ratio": 0.578, "NY Labor Force Level": 9825046.0, "NY Labor Force Participation Rate": 0.606, "NY Unemployment Level": 454793.0, "NY Unemployment Rate": 0.046, "U.S. Employment-Population Ratio": 0.601, "U.S. Labor Force Participation Rate": 0.627, "U.S. Unemployment Rate": 0.042}, {"time": "2017-12-01", "NY Employment Level": 9361966.0, "NY Employment-Population Ratio": 0.5770000000000001, "NY Labor Force Level": 9810886.0, "NY Labor Force Participation Rate": 0.605, "NY Unemployment Level": 448920.0, "NY Unemployment Rate": 0.046, "U.S. Employment-Population Ratio": 0.601, "U.S. Labor Force Participation Rate": 0.627, "U.S. Unemployment Rate": 0.040999999999999995}, {"time": "2018-01-01", "NY Employment Level": 9361990.0, "NY Employment-Population Ratio": 0.5770000000000001, "NY Labor Force Level": 9803080.0, "NY Labor Force Participation Rate": 0.605, "NY Unemployment Level": 441090.0, "NY Unemployment Rate": 0.045, "U.S. Employment-Population Ratio": 0.601, "U.S. Labor Force Participation Rate": 0.627, "U.S. Unemployment Rate": 0.04}, {"time": "2018-02-01", "NY Employment Level": 9372131.0, "NY Employment-Population Ratio": 0.578, "NY Labor Force Level": 9804282.0, "NY Labor Force Participation Rate": 0.605, "NY Unemployment Level": 432151.0, "NY Unemployment Rate": 0.044000000000000004, "U.S. Employment-Population Ratio": 0.604, "U.S. Labor Force Participation Rate": 0.63, "U.S. Unemployment Rate": 0.040999999999999995}, {"time": "2018-03-01", "NY Employment Level": 9390650.0, "NY Employment-Population Ratio": 0.579, "NY Labor Force Level": 9813082.0, "NY Labor Force Participation Rate": 0.605, "NY Unemployment Level": 422432.0, "NY Unemployment Rate": 0.043, "U.S. Employment-Population Ratio": 0.604, "U.S. Labor Force Participation Rate": 0.629, "U.S. Unemployment Rate": 0.04}, {"time": "2018-04-01", "NY Employment Level": 9411705.0, "NY Employment-Population Ratio": 0.58, "NY Labor Force Level": 9823863.0, "NY Labor Force Participation Rate": 0.606, "NY Unemployment Level": 412158.0, "NY Unemployment Rate": 0.042, "U.S. Employment-Population Ratio": 0.604, "U.S. Labor Force Participation Rate": 0.629, "U.S. Unemployment Rate": 0.04}, {"time": "2018-05-01", "NY Employment Level": 9428535.0, "NY Employment-Population Ratio": 0.581, "NY Labor Force Level": 9830800.0, "NY Labor Force Participation Rate": 0.606, "NY Unemployment Level": 402265.0, "NY Unemployment Rate": 0.040999999999999995, "U.S. Employment-Population Ratio": 0.605, "U.S. Labor Force Participation Rate": 0.629, "U.S. Unemployment Rate": 0.038}, {"time": "2018-06-01", "NY Employment Level": 9438890.0, "NY Employment-Population Ratio": 0.5820000000000001, "NY Labor Force Level": 9832509.0, "NY Labor Force Participation Rate": 0.606, "NY Unemployment Level": 393619.0, "NY Unemployment Rate": 0.04, "U.S. Employment-Population Ratio": 0.605, "U.S. Labor Force Participation Rate": 0.63, "U.S. Unemployment Rate": 0.04}, {"time": "2018-07-01", "NY Employment Level": 9443658.0, "NY Employment-Population Ratio": 0.5820000000000001, "NY Labor Force Level": 9830902.0, "NY Labor Force Participation Rate": 0.606, "NY Unemployment Level": 387244.0, "NY Unemployment Rate": 0.039, "U.S. Employment-Population Ratio": 0.606, "U.S. Labor Force Participation Rate": 0.63, "U.S. Unemployment Rate": 0.038}, {"time": "2018-08-01", "NY Employment Level": 9445452.0, "NY Employment-Population Ratio": 0.5820000000000001, "NY Labor Force Level": 9830123.0, "NY Labor Force Participation Rate": 0.605, "NY Unemployment Level": 384671.0, "NY Unemployment Rate": 0.039, "U.S. Employment-Population Ratio": 0.603, "U.S. Labor Force Participation Rate": 0.626, "U.S. Unemployment Rate": 0.038}, {"time": "2018-09-01", "NY Employment Level": 9445333.0, "NY Employment-Population Ratio": 0.5820000000000001, "NY Labor Force Level": 9831476.0, "NY Labor Force Participation Rate": 0.605, "NY Unemployment Level": 386143.0, "NY Unemployment Rate": 0.039, "U.S. Employment-Population Ratio": 0.604, "U.S. Labor Force Participation Rate": 0.628, "U.S. Unemployment Rate": 0.037000000000000005}, {"time": "2018-10-01", "NY Employment Level": 9445441.0, "NY Employment-Population Ratio": 0.581, "NY Labor Force Level": 9835265.0, "NY Labor Force Participation Rate": 0.605, "NY Unemployment Level": 389824.0, "NY Unemployment Rate": 0.04, "U.S. Employment-Population Ratio": 0.605, "U.S. Labor Force Participation Rate": 0.629, "U.S. Unemployment Rate": 0.038}, {"time": "2018-11-01", "NY Employment Level": 9447743.0, "NY Employment-Population Ratio": 0.581, "NY Labor Force Level": 9840824.0, "NY Labor Force Participation Rate": 0.606, "NY Unemployment Level": 393081.0, "NY Unemployment Rate": 0.04, "U.S. Employment-Population Ratio": 0.606, "U.S. Labor Force Participation Rate": 0.629, "U.S. Unemployment Rate": 0.038}, {"time": "2018-12-01", "NY Employment Level": 9452106.0, "NY Employment-Population Ratio": 0.5820000000000001, "NY Labor Force Level": 9846342.0, "NY Labor Force Participation Rate": 0.606, "NY Unemployment Level": 394236.0, "NY Unemployment Rate": 0.04, "U.S. Employment-Population Ratio": 0.606, "U.S. Labor Force Participation Rate": 0.63, "U.S. Unemployment Rate": 0.039}, {"time": "2019-01-01", "NY Employment Level": 9456377.0, "NY Employment-Population Ratio": 0.5820000000000001, "NY Labor Force Level": 9848899.0, "NY Labor Force Participation Rate": 0.606, "NY Unemployment Level": 392522.0, "NY Unemployment Rate": 0.04, "U.S. Employment-Population Ratio": 0.606, "U.S. Labor Force Participation Rate": 0.631, "U.S. Unemployment Rate": 0.04}, {"time": "2019-02-01", "NY Employment Level": 9459485.0, "NY Employment-Population Ratio": 0.5820000000000001, "NY Labor Force Level": 9846753.0, "NY Labor Force Participation Rate": 0.606, "NY Unemployment Level": 387268.0, "NY Unemployment Rate": 0.039, "U.S. Employment-Population Ratio": 0.607, "U.S. Labor Force Participation Rate": 0.631, "U.S. Unemployment Rate": 0.038}, {"time": "2019-03-01", "NY Employment Level": 9461113.0, "NY Employment-Population Ratio": 0.5820000000000001, "NY Labor Force Level": 9841664.0, "NY Labor Force Participation Rate": 0.606, "NY Unemployment Level": 380551.0, "NY Unemployment Rate": 0.039, "U.S. Employment-Population Ratio": 0.606, "U.S. Labor Force Participation Rate": 0.63, "U.S. Unemployment Rate": 0.038}, {"time": "2019-04-01", "NY Employment Level": 9463035.0, "NY Employment-Population Ratio": 0.5820000000000001, "NY Labor Force Level": 9837363.0, "NY Labor Force Participation Rate": 0.605, "NY Unemployment Level": 374328.0, "NY Unemployment Rate": 0.038, "U.S. Employment-Population Ratio": 0.605, "U.S. Labor Force Participation Rate": 0.628, "U.S. Unemployment Rate": 0.037000000000000005}, {"time": "2019-05-01", "NY Employment Level": 9466372.0, "NY Employment-Population Ratio": 0.583, "NY Labor Force Level": 9837115.0, "NY Labor Force Participation Rate": 0.605, "NY Unemployment Level": 370743.0, "NY Unemployment Rate": 0.038, "U.S. Employment-Population Ratio": 0.606, "U.S. Labor Force Participation Rate": 0.629, "U.S. Unemployment Rate": 0.036000000000000004}, {"time": "2019-06-01", "NY Employment Level": 9470995.0, "NY Employment-Population Ratio": 0.583, "NY Labor Force Level": 9842215.0, "NY Labor Force Participation Rate": 0.606, "NY Unemployment Level": 371220.0, "NY Unemployment Rate": 0.038, "U.S. Employment-Population Ratio": 0.607, "U.S. Labor Force Participation Rate": 0.63, "U.S. Unemployment Rate": 0.036000000000000004}, {"time": "2019-07-01", "NY Employment Level": 9476011.0, "NY Employment-Population Ratio": 0.583, "NY Labor Force Level": 9851433.0, "NY Labor Force Participation Rate": 0.606, "NY Unemployment Level": 375422.0, "NY Unemployment Rate": 0.038, "U.S. Employment-Population Ratio": 0.608, "U.S. Labor Force Participation Rate": 0.631, "U.S. Unemployment Rate": 0.037000000000000005}, {"time": "2019-08-01", "NY Employment Level": 9482245.0, "NY Employment-Population Ratio": 0.583, "NY Labor Force Level": 9863438.0, "NY Labor Force Participation Rate": 0.607, "NY Unemployment Level": 381193.0, "NY Unemployment Rate": 0.039, "U.S. Employment-Population Ratio": 0.608, "U.S. Labor Force Participation Rate": 0.631, "U.S. Unemployment Rate": 0.036000000000000004}, {"time": "2019-09-01", "NY Employment Level": 9494954.0, "NY Employment-Population Ratio": 0.584, "NY Labor Force Level": 9879755.0, "NY Labor Force Participation Rate": 0.608, "NY Unemployment Level": 384801.0, "NY Unemployment Rate": 0.039, "U.S. Employment-Population Ratio": 0.61, "U.S. Labor Force Participation Rate": 0.632, "U.S. Unemployment Rate": 0.035}, {"time": "2019-10-01", "NY Employment Level": 9511804.0, "NY Employment-Population Ratio": 0.585, "NY Labor Force Level": 9899509.0, "NY Labor Force Participation Rate": 0.609, "NY Unemployment Level": 387705.0, "NY Unemployment Rate": 0.039, "U.S. Employment-Population Ratio": 0.61, "U.S. Labor Force Participation Rate": 0.633, "U.S. Unemployment Rate": 0.036000000000000004}, {"time": "2019-11-01", "NY Employment Level": 9526610.0, "NY Employment-Population Ratio": 0.586, "NY Labor Force Level": 9918398.0, "NY Labor Force Participation Rate": 0.61, "NY Unemployment Level": 391788.0, "NY Unemployment Rate": 0.04, "U.S. Employment-Population Ratio": 0.61, "U.S. Labor Force Participation Rate": 0.633, "U.S. Unemployment Rate": 0.036000000000000004}, {"time": "2019-12-01", "NY Employment Level": 9530737.0, "NY Employment-Population Ratio": 0.586, "NY Labor Force Level": 9928423.0, "NY Labor Force Participation Rate": 0.611, "NY Unemployment Level": 397686.0, "NY Unemployment Rate": 0.04, "U.S. Employment-Population Ratio": 0.611, "U.S. Labor Force Participation Rate": 0.633, "U.S. Unemployment Rate": 0.036000000000000004}, {"time": "2020-01-01", "NY Employment Level": 9518640.0, "NY Employment-Population Ratio": 0.585, "NY Labor Force Level": 9923358.0, "NY Labor Force Participation Rate": 0.61, "NY Unemployment Level": 404718.0, "NY Unemployment Rate": 0.040999999999999995, "U.S. Employment-Population Ratio": 0.611, "U.S. Labor Force Participation Rate": 0.633, "U.S. Unemployment Rate": 0.036000000000000004}, {"time": "2020-02-01", "NY Employment Level": 9488885.0, "NY Employment-Population Ratio": 0.584, "NY Labor Force Level": 9901482.0, "NY Labor Force Participation Rate": 0.609, "NY Unemployment Level": 412597.0, "NY Unemployment Rate": 0.042, "U.S. Employment-Population Ratio": 0.611, "U.S. Labor Force Participation Rate": 0.633, "U.S. Unemployment Rate": 0.035}, {"time": "2020-03-01", "NY Employment Level": 9448828.0, "NY Employment-Population Ratio": 0.581, "NY Labor Force Level": 9867923.0, "NY Labor Force Participation Rate": 0.607, "NY Unemployment Level": 419095.0, "NY Unemployment Rate": 0.042, "U.S. Employment-Population Ratio": 0.598, "U.S. Labor Force Participation Rate": 0.626, "U.S. Unemployment Rate": 0.044000000000000004}, {"time": "2020-04-01", "NY Employment Level": 7690871.0, "NY Employment-Population Ratio": 0.473, "NY Labor Force Level": 9119448.0, "NY Labor Force Participation Rate": 0.561, "NY Unemployment Level": 1428577.0, "NY Unemployment Rate": 0.157, "U.S. Employment-Population Ratio": 0.512, "U.S. Labor Force Participation Rate": 0.601, "U.S. Unemployment Rate": 0.14800000000000002}, {"time": "2020-05-01", "NY Employment Level": 7843927.0, "NY Employment-Population Ratio": 0.483, "NY Labor Force Level": 9419207.0, "NY Labor Force Participation Rate": 0.58, "NY Unemployment Level": 1575280.0, "NY Unemployment Rate": 0.16699999999999998, "U.S. Employment-Population Ratio": 0.527, "U.S. Labor Force Participation Rate": 0.608, "U.S. Unemployment Rate": 0.132}, {"time": "2020-06-01", "NY Employment Level": 8210170.0, "NY Employment-Population Ratio": 0.507, "NY Labor Force Level": 9505600.0, "NY Labor Force Participation Rate": 0.586, "NY Unemployment Level": 1295430.0, "NY Unemployment Rate": 0.136, "U.S. Employment-Population Ratio": 0.547, "U.S. Labor Force Participation Rate": 0.615, "U.S. Unemployment Rate": 0.11}, {"time": "2020-07-01", "NY Employment Level": 8347465.0, "NY Employment-Population Ratio": 0.516, "NY Labor Force Level": 9545521.0, "NY Labor Force Participation Rate": 0.59, "NY Unemployment Level": 1198056.0, "NY Unemployment Rate": 0.126, "U.S. Employment-Population Ratio": 0.552, "U.S. Labor Force Participation Rate": 0.615, "U.S. Unemployment Rate": 0.102}, {"time": "2020-08-01", "NY Employment Level": 8454995.0, "NY Employment-Population Ratio": 0.523, "NY Labor Force Level": 9483036.0, "NY Labor Force Participation Rate": 0.586, "NY Unemployment Level": 1028041.0, "NY Unemployment Rate": 0.10800000000000001, "U.S. Employment-Population Ratio": 0.565, "U.S. Labor Force Participation Rate": 0.617, "U.S. Unemployment Rate": 0.084}, {"time": "2020-09-01", "NY Employment Level": 8551410.0, "NY Employment-Population Ratio": 0.529, "NY Labor Force Level": 9517449.0, "NY Labor Force Participation Rate": 0.589, "NY Unemployment Level": 966039.0, "NY Unemployment Rate": 0.102, "U.S. Employment-Population Ratio": 0.5660000000000001, "U.S. Labor Force Participation Rate": 0.614, "U.S. Unemployment Rate": 0.078}, {"time": "2020-10-01", "NY Employment Level": 8611651.0, "NY Employment-Population Ratio": 0.5329999999999999, "NY Labor Force Level": 9485291.0, "NY Labor Force Participation Rate": 0.5870000000000001, "NY Unemployment Level": 873640.0, "NY Unemployment Rate": 0.092, "U.S. Employment-Population Ratio": 0.575, "U.S. Labor Force Participation Rate": 0.617, "U.S. Unemployment Rate": 0.069}, {"time": "2020-11-01", "NY Employment Level": 8655601.0, "NY Employment-Population Ratio": 0.536, "NY Labor Force Level": 9505123.0, "NY Labor Force Participation Rate": 0.589, "NY Unemployment Level": 849522.0, "NY Unemployment Rate": 0.08900000000000001, "U.S. Employment-Population Ratio": 0.574, "U.S. Labor Force Participation Rate": 0.615, "U.S. Unemployment Rate": 0.067}, {"time": "2020-12-01", "NY Employment Level": 8682308.0, "NY Employment-Population Ratio": 0.5379999999999999, "NY Labor Force Level": 9513387.0, "NY Labor Force Participation Rate": 0.59, "NY Unemployment Level": 831079.0, "NY Unemployment Rate": 0.087, "U.S. Employment-Population Ratio": 0.574, "U.S. Labor Force Participation Rate": 0.615, "U.S. Unemployment Rate": 0.067}, {"time": "2021-01-01", "NY Employment Level": 8749662.0, "NY Employment-Population Ratio": 0.54, "NY Labor Force Level": 9564884.0, "NY Labor Force Participation Rate": 0.591, "NY Unemployment Level": 815222.0, "NY Unemployment Rate": 0.085, "U.S. Employment-Population Ratio": 0.574, "U.S. Labor Force Participation Rate": 0.614, "U.S. Unemployment Rate": 0.064}, {"time": "2021-02-01", "NY Employment Level": 8769235.0, "NY Employment-Population Ratio": 0.542, "NY Labor Force Level": 9567436.0, "NY Labor Force Participation Rate": 0.5920000000000001, "NY Unemployment Level": 798201.0, "NY Unemployment Rate": 0.083, "U.S. Employment-Population Ratio": 0.5760000000000001, "U.S. Labor Force Participation Rate": 0.614, "U.S. Unemployment Rate": 0.062}, {"time": "2021-03-01", "NY Employment Level": 8797725.0, "NY Employment-Population Ratio": 0.545, "NY Labor Force Level": 9572842.0, "NY Labor Force Participation Rate": 0.593, "NY Unemployment Level": 775117.0, "NY Unemployment Rate": 0.081, "U.S. Employment-Population Ratio": 0.5770000000000001, "U.S. Labor Force Participation Rate": 0.615, "U.S. Unemployment Rate": 0.061}, {"time": "2021-04-01", "NY Employment Level": 8831174.0, "NY Employment-Population Ratio": 0.547, "NY Labor Force Level": 9589109.0, "NY Labor Force Participation Rate": 0.594, "NY Unemployment Level": 757935.0, "NY Unemployment Rate": 0.079, "U.S. Employment-Population Ratio": 0.578, "U.S. Labor Force Participation Rate": 0.616, "U.S. Unemployment Rate": 0.061}, {"time": "2021-05-01", "NY Employment Level": 8866350.0, "NY Employment-Population Ratio": 0.55, "NY Labor Force Level": 9583194.0, "NY Labor Force Participation Rate": 0.594, "NY Unemployment Level": 716844.0, "NY Unemployment Rate": 0.075, "U.S. Employment-Population Ratio": 0.58, "U.S. Labor Force Participation Rate": 0.616, "U.S. Unemployment Rate": 0.057999999999999996}, {"time": "2021-06-01", "NY Employment Level": 8899470.0, "NY Employment-Population Ratio": 0.5529999999999999, "NY Labor Force Level": 9617457.0, "NY Labor Force Participation Rate": 0.597, "NY Unemployment Level": 717987.0, "NY Unemployment Rate": 0.075, "U.S. Employment-Population Ratio": 0.581, "U.S. Labor Force Participation Rate": 0.617, "U.S. Unemployment Rate": 0.059000000000000004}, {"time": "2021-07-01", "NY Employment Level": 8927950.0, "NY Employment-Population Ratio": 0.555, "NY Labor Force Level": 9603748.0, "NY Labor Force Participation Rate": 0.597, "NY Unemployment Level": 675798.0, "NY Unemployment Rate": 0.07, "U.S. Employment-Population Ratio": 0.584, "U.S. Labor Force Participation Rate": 0.618, "U.S. Unemployment Rate": 0.054000000000000006}, {"time": "2021-08-01", "NY Employment Level": 8957817.0, "NY Employment-Population Ratio": 0.557, "NY Labor Force Level": 9606711.0, "NY Labor Force Participation Rate": 0.597, "NY Unemployment Level": 648894.0, "NY Unemployment Rate": 0.068, "U.S. Employment-Population Ratio": 0.586, "U.S. Labor Force Participation Rate": 0.617, "U.S. Unemployment Rate": 0.051}, {"time": "2021-09-01", "NY Employment Level": 8991367.0, "NY Employment-Population Ratio": 0.5589999999999999, "NY Labor Force Level": 9586797.0, "NY Labor Force Participation Rate": 0.596, "NY Unemployment Level": 595430.0, "NY Unemployment Rate": 0.062, "U.S. Employment-Population Ratio": 0.588, "U.S. Labor Force Participation Rate": 0.617, "U.S. Unemployment Rate": 0.047}, {"time": "2021-10-01", "NY Employment Level": 9033245.0, "NY Employment-Population Ratio": 0.562, "NY Labor Force Level": 9597109.0, "NY Labor Force Participation Rate": 0.597, "NY Unemployment Level": 563864.0, "NY Unemployment Rate": 0.059000000000000004, "U.S. Employment-Population Ratio": 0.59, "U.S. Labor Force Participation Rate": 0.618, "U.S. Unemployment Rate": 0.045}, {"time": "2021-11-01", "NY Employment Level": 9077094.0, "NY Employment-Population Ratio": 0.565, "NY Labor Force Level": 9608605.0, "NY Labor Force Participation Rate": 0.598, "NY Unemployment Level": 531511.0, "NY Unemployment Rate": 0.055, "U.S. Employment-Population Ratio": 0.593, "U.S. Labor Force Participation Rate": 0.619, "U.S. Unemployment Rate": 0.040999999999999995}, {"time": "2021-12-01", "NY Employment Level": 9120733.0, "NY Employment-Population Ratio": 0.568, "NY Labor Force Level": 9643606.0, "NY Labor Force Participation Rate": 0.6, "NY Unemployment Level": 522873.0, "NY Unemployment Rate": 0.054000000000000006, "U.S. Employment-Population Ratio": 0.595, "U.S. Labor Force Participation Rate": 0.62, "U.S. Unemployment Rate": 0.039}, {"time": "2022-01-01", "NY Employment Level": 9160745.0, "NY Employment-Population Ratio": 0.57, "NY Labor Force Level": 9660517.0, "NY Labor Force Participation Rate": 0.601, "NY Unemployment Level": 499772.0, "NY Unemployment Rate": 0.052000000000000005, "U.S. Employment-Population Ratio": 0.597, "U.S. Labor Force Participation Rate": 0.622, "U.S. Unemployment Rate": 0.04}, {"time": "2022-02-01", "NY Employment Level": 9195716.0, "NY Employment-Population Ratio": 0.573, "NY Labor Force Level": 9661992.0, "NY Labor Force Participation Rate": 0.602, "NY Unemployment Level": 466276.0, "NY Unemployment Rate": 0.048, "U.S. Employment-Population Ratio": 0.599, "U.S. Labor Force Participation Rate": 0.623, "U.S. Unemployment Rate": 0.039}, {"time": "2022-03-01", "NY Employment Level": 9223128.0, "NY Employment-Population Ratio": 0.575, "NY Labor Force Level": 9665260.0, "NY Labor Force Participation Rate": 0.602, "NY Unemployment Level": 442132.0, "NY Unemployment Rate": 0.046, "U.S. Employment-Population Ratio": 0.601, "U.S. Labor Force Participation Rate": 0.624, "U.S. Unemployment Rate": 0.037000000000000005}, {"time": "2022-04-01", "NY Employment Level": 9245244.0, "NY Employment-Population Ratio": 0.5760000000000001, "NY Labor Force Level": 9676884.0, "NY Labor Force Participation Rate": 0.603, "NY Unemployment Level": 431640.0, "NY Unemployment Rate": 0.045, "U.S. Employment-Population Ratio": 0.599, "U.S. Labor Force Participation Rate": 0.622, "U.S. Unemployment Rate": 0.037000000000000005}, {"time": "2022-05-01", "NY Employment Level": 9261586.0, "NY Employment-Population Ratio": 0.5770000000000001, "NY Labor Force Level": 9678221.0, "NY Labor Force Participation Rate": 0.603, "NY Unemployment Level": 416635.0, "NY Unemployment Rate": 0.043, "U.S. Employment-Population Ratio": 0.601, "U.S. Labor Force Participation Rate": 0.623, "U.S. Unemployment Rate": 0.036000000000000004}, {"time": "2022-06-01", "NY Employment Level": 9275015.0, "NY Employment-Population Ratio": 0.578, "NY Labor Force Level": 9680247.0, "NY Labor Force Participation Rate": 0.604, "NY Unemployment Level": 405232.0, "NY Unemployment Rate": 0.042, "U.S. Employment-Population Ratio": 0.599, "U.S. Labor Force Participation Rate": 0.622, "U.S. Unemployment Rate": 0.036000000000000004}, {"time": "2022-07-01", "NY Employment Level": 9284900.0, "NY Employment-Population Ratio": 0.579, "NY Labor Force Level": 9671387.0, "NY Labor Force Participation Rate": 0.603, "NY Unemployment Level": 386487.0, "NY Unemployment Rate": 0.04, "U.S. Employment-Population Ratio": 0.6, "U.S. Labor Force Participation Rate": 0.621, "U.S. Unemployment Rate": 0.035}, {"time": "2022-08-01", "NY Employment Level": 9291395.0, "NY Employment-Population Ratio": 0.579, "NY Labor Force Level": 9657851.0, "NY Labor Force Participation Rate": 0.602, "NY Unemployment Level": 366456.0, "NY Unemployment Rate": 0.038, "U.S. Employment-Population Ratio": 0.601, "U.S. Labor Force Participation Rate": 0.623, "U.S. Unemployment Rate": 0.036000000000000004}, {"time": "2022-09-01", "NY Employment Level": 9297413.0, "NY Employment-Population Ratio": 0.579, "NY Labor Force Level": 9675983.0, "NY Labor Force Participation Rate": 0.603, "NY Unemployment Level": 378570.0, "NY Unemployment Rate": 0.039, "U.S. Employment-Population Ratio": 0.601, "U.S. Labor Force Participation Rate": 0.622, "U.S. Unemployment Rate": 0.035}, {"time": "2022-10-01", "NY Employment Level": 9306831.0, "NY Employment-Population Ratio": 0.579, "NY Labor Force Level": 9694389.0, "NY Labor Force Participation Rate": 0.603, "NY Unemployment Level": 387558.0, "NY Unemployment Rate": 0.04, "U.S. Employment-Population Ratio": 0.6, "U.S. Labor Force Participation Rate": 0.622, "U.S. Unemployment Rate": 0.036000000000000004}, {"time": "2022-11-01", "NY Employment Level": 9322123.0, "NY Employment-Population Ratio": 0.58, "NY Labor Force Level": 9714705.0, "NY Labor Force Participation Rate": 0.604, "NY Unemployment Level": 392582.0, "NY Unemployment Rate": 0.04, "U.S. Employment-Population Ratio": 0.599, "U.S. Labor Force Participation Rate": 0.621, "U.S. Unemployment Rate": 0.036000000000000004}, {"time": "2022-12-01", "NY Employment Level": 9342011.0, "NY Employment-Population Ratio": 0.581, "NY Labor Force Level": 9735970.0, "NY Labor Force Participation Rate": 0.605, "NY Unemployment Level": 393959.0, "NY Unemployment Rate": 0.04, "U.S. Employment-Population Ratio": 0.601, "U.S. Labor Force Participation Rate": 0.623, "U.S. Unemployment Rate": 0.035}, {"time": "2023-01-01", "NY Employment Level": 9365308.0, "NY Employment-Population Ratio": 0.5820000000000001, "NY Labor Force Level": 9758797.0, "NY Labor Force Participation Rate": 0.607, "NY Unemployment Level": 393489.0, "NY Unemployment Rate": 0.04, "U.S. Employment-Population Ratio": 0.602, "U.S. Labor Force Participation Rate": 0.624, "U.S. Unemployment Rate": 0.035}, {"time": "2023-02-01", "NY Employment Level": 9390605.0, "NY Employment-Population Ratio": 0.583, "NY Labor Force Level": 9782303.0, "NY Labor Force Participation Rate": 0.608, "NY Unemployment Level": 391698.0, "NY Unemployment Rate": 0.04, "U.S. Employment-Population Ratio": 0.603, "U.S. Labor Force Participation Rate": 0.625, "U.S. Unemployment Rate": 0.036000000000000004}, {"time": "2023-03-01", "NY Employment Level": 9416935.0, "NY Employment-Population Ratio": 0.585, "NY Labor Force Level": 9805337.0, "NY Labor Force Participation Rate": 0.609, "NY Unemployment Level": 388402.0, "NY Unemployment Rate": 0.04, "U.S. Employment-Population Ratio": 0.604, "U.S. Labor Force Participation Rate": 0.626, "U.S. Unemployment Rate": 0.035}, {"time": "2023-04-01", "NY Employment Level": 9441434.0, "NY Employment-Population Ratio": 0.586, "NY Labor Force Level": 9825999.0, "NY Labor Force Participation Rate": 0.61, "NY Unemployment Level": 384565.0, "NY Unemployment Rate": 0.039, "U.S. Employment-Population Ratio": 0.604, "U.S. Labor Force Participation Rate": 0.626, "U.S. Unemployment Rate": 0.034}, {"time": "2023-05-01", "NY Employment Level": 9459823.0, "NY Employment-Population Ratio": 0.5870000000000001, "NY Labor Force Level": 9842980.0, "NY Labor Force Participation Rate": 0.611, "NY Unemployment Level": 383157.0, "NY Unemployment Rate": 0.039, "U.S. Employment-Population Ratio": 0.603, "U.S. Labor Force Participation Rate": 0.626, "U.S. Unemployment Rate": 0.036000000000000004}, {"time": "2023-06-01", "NY Employment Level": 9471938.0, "NY Employment-Population Ratio": 0.5870000000000001, "NY Labor Force Level": 9857028.0, "NY Labor Force Participation Rate": 0.611, "NY Unemployment Level": 385090.0, "NY Unemployment Rate": 0.039, "U.S. Employment-Population Ratio": 0.603, "U.S. Labor Force Participation Rate": 0.626, "U.S. Unemployment Rate": 0.036000000000000004}, {"time": "2023-07-01", "NY Employment Level": 9479656.0, "NY Employment-Population Ratio": 0.5870000000000001, "NY Labor Force Level": 9869841.0, "NY Labor Force Participation Rate": 0.612, "NY Unemployment Level": 390185.0, "NY Unemployment Rate": 0.04, "U.S. Employment-Population Ratio": 0.604, "U.S. Labor Force Participation Rate": 0.626, "U.S. Unemployment Rate": 0.035}, {"time": "2023-08-01", "NY Employment Level": 9482979.0, "NY Employment-Population Ratio": 0.5870000000000001, "NY Labor Force Level": 9880115.0, "NY Labor Force Participation Rate": 0.611, "NY Unemployment Level": 397136.0, "NY Unemployment Rate": 0.04, "U.S. Employment-Population Ratio": 0.604, "U.S. Labor Force Participation Rate": 0.628, "U.S. Unemployment Rate": 0.037000000000000005}, {"time": "2023-09-01", "NY Employment Level": 9483210.0, "NY Employment-Population Ratio": 0.586, "NY Labor Force Level": 9887061.0, "NY Labor Force Participation Rate": 0.611, "NY Unemployment Level": 403851.0, "NY Unemployment Rate": 0.040999999999999995, "U.S. Employment-Population Ratio": 0.604, "U.S. Labor Force Participation Rate": 0.627, "U.S. Unemployment Rate": 0.037000000000000005}, {"time": "2023-10-01", "NY Employment Level": 9482042.0, "NY Employment-Population Ratio": 0.585, "NY Labor Force Level": 9890984.0, "NY Labor Force Participation Rate": 0.611, "NY Unemployment Level": 408942.0, "NY Unemployment Rate": 0.040999999999999995, "U.S. Employment-Population Ratio": 0.602, "U.S. Labor Force Participation Rate": 0.626, "U.S. Unemployment Rate": 0.039}, {"time": "2023-11-01", "NY Employment Level": 9481072.0, "NY Employment-Population Ratio": 0.585, "NY Labor Force Level": 9892851.0, "NY Labor Force Participation Rate": 0.61, "NY Unemployment Level": 411779.0, "NY Unemployment Rate": 0.042, "U.S. Employment-Population Ratio": 0.604, "U.S. Labor Force Participation Rate": 0.628, "U.S. Unemployment Rate": 0.037000000000000005}, {"time": "2023-12-01", "NY Employment Level": 9482447.0, "NY Employment-Population Ratio": 0.584, "NY Labor Force Level": 9894409.0, "NY Labor Force Participation Rate": 0.61, "NY Unemployment Level": 411962.0, "NY Unemployment Rate": 0.042, "U.S. Employment-Population Ratio": 0.601, "U.S. Labor Force Participation Rate": 0.625, "U.S. Unemployment Rate": 0.038}, {"time": "2024-01-01", "NY Employment Level": 9485047.0, "NY Employment-Population Ratio": 0.584, "NY Labor Force Level": 9894797.0, "NY Labor Force Participation Rate": 0.609, "NY Unemployment Level": 409750.0, "NY Unemployment Rate": 0.040999999999999995, "U.S. Employment-Population Ratio": 0.602, "U.S. Labor Force Participation Rate": 0.625, "U.S. Unemployment Rate": 0.037000000000000005}, {"time": "2024-02-01", "NY Employment Level": 9489609.0, "NY Employment-Population Ratio": 0.584, "NY Labor Force Level": 9897589.0, "NY Labor Force Participation Rate": 0.609, "NY Unemployment Level": 407980.0, "NY Unemployment Rate": 0.040999999999999995, "U.S. Employment-Population Ratio": 0.602, "U.S. Labor Force Participation Rate": 0.626, "U.S. Unemployment Rate": 0.039}, {"time": "2024-03-01", "NY Employment Level": 9494839.0, "NY Employment-Population Ratio": 0.583, "NY Labor Force Level": 9904307.0, "NY Labor Force Participation Rate": 0.609, "NY Unemployment Level": 409468.0, "NY Unemployment Rate": 0.040999999999999995, "U.S. Employment-Population Ratio": 0.603, "U.S. Labor Force Participation Rate": 0.627, "U.S. Unemployment Rate": 0.039}, {"time": "2024-04-01", "NY Employment Level": 9501252.0, "NY Employment-Population Ratio": 0.583, "NY Labor Force Level": 9914778.0, "NY Labor Force Participation Rate": 0.609, "NY Unemployment Level": 413526.0, "NY Unemployment Rate": 0.042, "U.S. Employment-Population Ratio": 0.602, "U.S. Labor Force Participation Rate": 0.626, "U.S. Unemployment Rate": 0.039}, {"time": "2024-05-01", "NY Employment Level": 9509659.0, "NY Employment-Population Ratio": 0.583, "NY Labor Force Level": 9927285.0, "NY Labor Force Participation Rate": 0.609, "NY Unemployment Level": 417626.0, "NY Unemployment Rate": 0.042, "U.S. Employment-Population Ratio": 0.601, "U.S. Labor Force Participation Rate": 0.626, "U.S. Unemployment Rate": 0.039}, {"time": "2024-06-01", "NY Employment Level": 9517357.0, "NY Employment-Population Ratio": 0.583, "NY Labor Force Level": 9937299.0, "NY Labor Force Participation Rate": 0.609, "NY Unemployment Level": 419942.0, "NY Unemployment Rate": 0.042, "U.S. Employment-Population Ratio": 0.6, "U.S. Labor Force Participation Rate": 0.626, "U.S. Unemployment Rate": 0.040999999999999995}, {"time": "2024-07-01", "NY Employment Level": 9522427.0, "NY Employment-Population Ratio": 0.583, "NY Labor Force Level": 9942561.0, "NY Labor Force Participation Rate": 0.608, "NY Unemployment Level": 420134.0, "NY Unemployment Rate": 0.042, "U.S. Employment-Population Ratio": 0.6, "U.S. Labor Force Participation Rate": 0.627, "U.S. Unemployment Rate": 0.042}, {"time": "2024-08-01", "NY Employment Level": 9526402.0, "NY Employment-Population Ratio": 0.583, "NY Labor Force Level": 9944781.0, "NY Labor Force Participation Rate": 0.608, "NY Unemployment Level": 418379.0, "NY Unemployment Rate": 0.042, "U.S. Employment-Population Ratio": 0.6, "U.S. Labor Force Participation Rate": 0.627, "U.S. Unemployment Rate": 0.042}, {"time": "2024-09-01", "NY Employment Level": 9529565.0, "NY Employment-Population Ratio": 0.583, "NY Labor Force Level": 9945041.0, "NY Labor Force Participation Rate": 0.608, "NY Unemployment Level": 415476.0, "NY Unemployment Rate": 0.042, "U.S. Employment-Population Ratio": 0.601, "U.S. Labor Force Participation Rate": 0.627, "U.S. Unemployment Rate": 0.040999999999999995}, {"time": "2024-10-01", "NY Employment Level": 9533035.0, "NY Employment-Population Ratio": 0.583, "NY Labor Force Level": 9944825.0, "NY Labor Force Participation Rate": 0.608, "NY Unemployment Level": 411790.0, "NY Unemployment Rate": 0.040999999999999995, "U.S. Employment-Population Ratio": 0.6, "U.S. Labor Force Participation Rate": 0.625, "U.S. Unemployment Rate": 0.040999999999999995}, {"time": "2024-11-01", "NY Employment Level": 9538060.0, "NY Employment-Population Ratio": 0.583, "NY Labor Force Level": 9946572.0, "NY Labor Force Participation Rate": 0.608, "NY Unemployment Level": 408512.0, "NY Unemployment Rate": 0.040999999999999995, "U.S. Employment-Population Ratio": 0.598, "U.S. Labor Force Participation Rate": 0.624, "U.S. Unemployment Rate": 0.042}, {"time": "2024-12-01", "NY Employment Level": 9544836.0, "NY Employment-Population Ratio": 0.583, "NY Labor Force Level": 9951364.0, "NY Labor Force Participation Rate": 0.608, "NY Unemployment Level": 406528.0, "NY Unemployment Rate": 0.040999999999999995, "U.S. Employment-Population Ratio": 0.599, "U.S. Labor Force Participation Rate": 0.625, "U.S. Unemployment Rate": 0.040999999999999995}, {"time": "2025-01-01", "NY Employment Level": 9552383.0, "NY Employment-Population Ratio": 0.584, "NY Labor Force Level": 9958025.0, "NY Labor Force Participation Rate": 0.609, "NY Unemployment Level": 405642.0, "NY Unemployment Rate": 0.040999999999999995, "U.S. Employment-Population Ratio": 0.601, "U.S. Labor Force Participation Rate": 0.626, "U.S. Unemployment Rate": 0.04}, {"time": "2025-02-01", "NY Employment Level": 9558366.0, "NY Employment-Population Ratio": 0.584, "NY Labor Force Level": 9963936.0, "NY Labor Force Participation Rate": 0.609, "NY Unemployment Level": 405570.0, "NY Unemployment Rate": 0.040999999999999995, "U.S. Employment-Population Ratio": 0.599, "U.S. Labor Force Participation Rate": 0.625, "U.S. Unemployment Rate": 0.042}, {"time": "2025-03-01", "NY Employment Level": 9560425.0, "NY Employment-Population Ratio": 0.584, "NY Labor Force Level": 9966391.0, "NY Labor Force Participation Rate": 0.609, "NY Unemployment Level": 405966.0, "NY Unemployment Rate": 0.040999999999999995, "U.S. Employment-Population Ratio": 0.599, "U.S. Labor Force Participation Rate": 0.625, "U.S. Unemployment Rate": 0.042}, {"time": "2025-04-01", "NY Employment Level": 9557556.0, "NY Employment-Population Ratio": 0.584, "NY Labor Force Level": 9966421.0, "NY Labor Force Participation Rate": 0.609, "NY Unemployment Level": 408865.0, "NY Unemployment Rate": 0.040999999999999995, "U.S. Employment-Population Ratio": 0.6, "U.S. Labor Force Participation Rate": 0.626, "U.S. Unemployment Rate": 0.042}, {"time": "2025-05-01", "NY Employment Level": 9550397.0, "NY Employment-Population Ratio": 0.584, "NY Labor Force Level": 9966598.0, "NY Labor Force Participation Rate": 0.609, "NY Unemployment Level": 416201.0, "NY Unemployment Rate": 0.042, "U.S. Employment-Population Ratio": 0.597, "U.S. Labor Force Participation Rate": 0.624, "U.S. Unemployment Rate": 0.043}, {"time": "2025-06-01", "NY Employment Level": 9543139.0, "NY Employment-Population Ratio": 0.583, "NY Labor Force Level": 9970634.0, "NY Labor Force Participation Rate": 0.609, "NY Unemployment Level": 427495.0, "NY Unemployment Rate": 0.043, "U.S. Employment-Population Ratio": 0.597, "U.S. Labor Force Participation Rate": 0.623, "U.S. Unemployment Rate": 0.040999999999999995}, {"time": "2025-07-01", "NY Employment Level": 9545360.0, "NY Employment-Population Ratio": 0.583, "NY Labor Force Level": 9986380.0, "NY Labor Force Participation Rate": 0.61, "NY Unemployment Level": 441020.0, "NY Unemployment Rate": 0.044000000000000004, "U.S. Employment-Population Ratio": 0.596, "U.S. Labor Force Participation Rate": 0.622, "U.S. Unemployment Rate": 0.043}, {"time": "2025-08-01", "NY Employment Level": 9558784.0, "NY Employment-Population Ratio": 0.584, "NY Labor Force Level": 10012631.0, "NY Labor Force Participation Rate": 0.612, "NY Unemployment Level": 453847.0, "NY Unemployment Rate": 0.045, "U.S. Employment-Population Ratio": 0.596, "U.S. Labor Force Participation Rate": 0.623, "U.S. Unemployment Rate": 0.043}, {"time": "2025-09-01", "NY Employment Level": 9580968.0, "NY Employment-Population Ratio": 0.585, "NY Labor Force Level": 10044581.0, "NY Labor Force Participation Rate": 0.613, "NY Unemployment Level": 463613.0, "NY Unemployment Rate": 0.046, "U.S. Employment-Population Ratio": 0.597, "U.S. Labor Force Participation Rate": 0.625, "U.S. Unemployment Rate": 0.044000000000000004}, {"time": "2025-11-01", "NY Employment Level": 9614116.0, "NY Employment-Population Ratio": 0.5870000000000001, "NY Labor Force Level": 10081101.0, "NY Labor Force Participation Rate": 0.616, "NY Unemployment Level": 466985.0, "NY Unemployment Rate": 0.046, "U.S. Employment-Population Ratio": 0.596, "U.S. Labor Force Participation Rate": 0.625, "U.S. Unemployment Rate": 0.045}, {"time": "2025-12-01", "NY Employment Level": 9615453.0, "NY Employment-Population Ratio": 0.5870000000000001, "NY Labor Force Level": 10080281.0, "NY Labor Force Participation Rate": 0.616, "NY Unemployment Level": 464828.0, "NY Unemployment Rate": 0.046, "U.S. Employment-Population Ratio": 0.597, "U.S. Labor Force Participation Rate": 0.624, "U.S. Unemployment Rate": 0.044000000000000004}, {"time": "2026-01-01", "NY Employment Level": 9639310.0, "NY Employment-Population Ratio": 0.589, "NY Labor Force Level": 10104683.0, "NY Labor Force Participation Rate": 0.617, "NY Unemployment Level": 465373.0, "NY Unemployment Rate": 0.046, "U.S. Employment-Population Ratio": 0.594, "U.S. Labor Force Participation Rate": 0.621, "U.S. Unemployment Rate": 0.043}, {"time": "2026-02-01", "NY Employment Level": null, "NY Employment-Population Ratio": null, "NY Labor Force Level": null, "NY Labor Force Participation Rate": null, "NY Unemployment Level": null, "NY Unemployment Rate": null, "U.S. Employment-Population Ratio": 0.593, "U.S. Labor Force Participation Rate": 0.62, "U.S. Unemployment Rate": 0.044000000000000004}, {"time": "2026-03-01", "NY Employment Level": null, "NY Employment-Population Ratio": null, "NY Labor Force Level": null, "NY Labor Force Participation Rate": null, "NY Unemployment Level": null, "NY Unemployment Rate": null, "U.S. Employment-Population Ratio": 0.5920000000000001, "U.S. Labor Force Participation Rate": 0.619, "U.S. Unemployment Rate": 0.043}]